<?xml version="1.0" encoding="utf-8" ?><dwsync><file name="archive.png" server="ftp.lolipop.jp//html/" local="3837232340" remote="3837229560" Dst="-1" /><file name="archive.svg" server="ftp.lolipop.jp//html/" local="3837232341" remote="3837229560" Dst="-1" /><file name="audio.png" server="ftp.lolipop.jp//html/" local="3837232341" remote="3837229560" Dst="-1" /><file name="audio.svg" server="ftp.lolipop.jp//html/" local="3837232341" remote="3837229560" Dst="-1" /><file name="code.png" server="ftp.lolipop.jp//html/" local="3837232341" remote="3837229560" Dst="-1" /><file name="code.svg" server="ftp.lolipop.jp//html/" local="3837232341" remote="3837229560" Dst="-1" /><file name="default.png" server="ftp.lolipop.jp//html/" local="3837232341" remote="3837229560" Dst="-1" /><file name="default.svg" server="ftp.lolipop.jp//html/" local="3837232341" remote="3837229560" Dst="-1" /><file name="document.png" server="ftp.lolipop.jp//html/" local="3837232342" remote="3837229560" Dst="-1" /><file name="document.svg" server="ftp.lolipop.jp//html/" local="3837232342" remote="3837229560" Dst="-1" /><file name="interactive.png" server="ftp.lolipop.jp//html/" local="3837232343" remote="3837229560" Dst="-1" /><file name="interactive.svg" server="ftp.lolipop.jp//html/" local="3837232343" remote="3837229560" Dst="-1" /><file name="spreadsheet.png" server="ftp.lolipop.jp//html/" local="3837232343" remote="3837229560" Dst="-1" /><file name="spreadsheet.svg" server="ftp.lolipop.jp//html/" local="3837232343" remote="3837229560" Dst="-1" /><file name="text.png" server="ftp.lolipop.jp//html/" local="3837232344" remote="3837229560" Dst="-1" /><file name="text.svg" server="ftp.lolipop.jp//html/" local="3837232344" remote="3837229560" Dst="-1" /><file name="video.png" server="ftp.lolipop.jp//html/" local="3837232344" remote="3837229560" Dst="-1" /><file name="video.svg" server="ftp.lolipop.jp//html/" local="3837232344" remote="3837229560" Dst="-1" /></dwsync>